sc_movie/__init__.py
sc_movie/omdb_lib.py
sc_movie-0.0.1.dist-info/LICENCE.txt
sc_movie-0.0.1.dist-info/METADATA
sc_movie-0.0.1.dist-info/WHEEL
sc_movie-0.0.1.dist-info/top_level.txt
sc_movie-0.0.1.dist-info/RECORD
